{
    "Version": "1.2",
    "Data": {
        "Source": "e:\\unreal project\\ue5_study\\boom_tank\\source\\boom_tank\\boom_tank.cpp",
        "ProvidedModule": "",
        "PCH": "e:\\unreal project\\ue5_study\\boom_tank\\intermediate\\build\\win64\\x64\\boom_tankeditor\\development\\engine\\sharedpch.engine.cpp20.h.pch",
        "Includes": [
            "e:\\unreal project\\ue5_study\\boom_tank\\intermediate\\build\\win64\\x64\\unrealeditor\\development\\boom_tank\\definitions.boom_tank.h",
            "e:\\unreal project\\ue5_study\\boom_tank\\source\\boom_tank\\boom_tank.h"
        ],
        "ImportedModules": [],
        "ImportedHeaderUnits": []
    }
}